test/__init__.py
test/test_textGenerator.py
text_generator/__init__.py
text_generator/test.py
text_generator/text_generator.py
text_generator-0.1.0.dist-info/DESCRIPTION.rst
text_generator-0.1.0.dist-info/METADATA
text_generator-0.1.0.dist-info/RECORD
text_generator-0.1.0.dist-info/WHEEL
text_generator-0.1.0.dist-info/entry_points.txt
text_generator-0.1.0.dist-info/metadata.json
text_generator-0.1.0.dist-info/top_level.txt
